pyhisto/__init__.py
pyhisto/bin.py
pyhisto/ghosthistogram.py
pyhisto/ghosthistogram2D.py
pyhisto/histogram.py
pyhisto/histogram2D.py
pyhisto/lazyhistogram.py
pyhisto/lazyhistogram2D.py
pyhisto/tools/__init__.py
pyhisto/tools/findpeaks.py
pyhisto/tools/gaussfit.py
pyhisto/tools/gaussrealfit.py
pyhisto/tools/parzen_estimator.py
pyhisto/tools/stats.py
pyhisto-0.1.2.dist-info/AUTHORS
pyhisto-0.1.2.dist-info/LICENSE
pyhisto-0.1.2.dist-info/METADATA
pyhisto-0.1.2.dist-info/WHEEL
pyhisto-0.1.2.dist-info/top_level.txt
pyhisto-0.1.2.dist-info/RECORD
